<?xml version='1.0' encoding='iso-8859-1'?>
<!DOCTYPE pregunta SYSTEM "./../../../../clase.dtd">
<p>
	<q0>
	</q0>
	<g0>
	</g0>
	<q>De  la  informaci贸n  proporcionada  en  el  gr谩fico 
sobre  adolescentes  de  nivel  primario  se  infiere 
que 
	</q>
	<q2>	
	</q2>
	<as r="R" correcta="1">
		<a>los docentes de las regiones de La Libertad y 
	Ucayali hacen bien su trabajo.</a>
		<a>el  n煤mero  de  nias  embarazadas  pude  incre- 
	mentarse en el ao en curso.</a>
		<a>la organizaci贸n Save the Children ha recogido 
	informaci贸n de todo el Per煤.</a>
		<a>la  desinformaci贸n  sobre  los  m茅todos  anticon- 
	ceptivos es un riesgo para todos.</a>
		<a>el  n煤mero  de  embarazos  en  Lima  es,  porcen- 
	tualmente, menor que en Ucayali.</a>
	</as>	
	<x>B.</x>
	<i></i>
	<x2>
	</x2>
	<i2></i2>
	<v></v>
</p>