<?xml version='1.0' encoding='iso-8859-1'?>
<!DOCTYPE pregunta SYSTEM "./../../../../clase.dtd">
<p>
	<q0>
	</q0>
	<g0>
	</g0>
	<q>El ojo del hurac치n Irma pas칩 por las islas Bahamas 
con una rapidez de 180 km/h en direcci칩n noroeste, 
formando 60췈 con la vertical. Dos horas despu칠s. 
Irma se intensific칩 convirti칠ndose en hurac치n de 
categor칤a 5 y cambi칩 de direcci칩n hac眼 el norte 
con una rapidez de 240 km/h. Luego de cinco horas 
desde que pas칩 por las Bahamas, 쯖u치n lejos de 
ellas se encontraba el ojo del hurac치n?
	</q>
	<q2>	
	</q2>
	<as r="R" correcta="2">
		<a></a>
		<a></a>
		<a></a>
		<a></a>
		<a></a>
	</as>	
	<x>C.</x>
	<i></i>
	<x2>
	</x2>
	<i2></i2>
	<v></v>
</p>