<?xml version='1.0' encoding='iso-8859-1'?>
<!DOCTYPE pregunta SYSTEM "./../../../../clase.dtd">
<p>
	<q0></q0>
	<g0></g0>
	<q>Juana, quien acaba de conseguir su primer em- 
pleo luego de terminar la universidad, est치 muy 
ilusionada con su pr칩ximo matrimonio; desea 
tener hijos y destacar en su trabajo. Juana est치 
en la etapa de la </q>
	<q2>	
	</q2>
	<as t="R" correcta="">
		<a>adolescencia.</a>
		<a>pubertad.</a>
		<a>adultez intermedia.</a>
		<a>adultez temprana.</a>
		<a>adultez avanzada.</a>
	</as>	
	<x></x>
	<i></i>
	<x2>Tema: Desarrollo humano 
El continuo proceso de cambios en diversos aspectos 
(f칤sicos, psicol칩gicos y sociales), que se da a lo 
largo del ciclo vital, es lo que define al desarrollo. 
Este involucra una sucesi칩n de etapas: infancia, 
ni吝z, adolescencia y adultez (otras clasificacio- 
nes comprenden etapas m치s espec칤ficas como la 
juventud y la senectud). 

An치lisis y argumentaci칩n 
De todas las etapas, la m치s extensa es la adultez, 
pues m치s de la mitad de nuestras vidas somos 
adultos. Por ello, dicha etapa se puede subdividir 
en tres etapas m치s precisas: la adultez temprana 
(20 - 40 a絪s), la adultez intermedia (40 - 65 a絪s) 
y la adultez avanzada (65 en adelante). 
Durante la adultez temprana, muchos cambios 
est치n relacionados con el logro o alcance de las  
metas del proyecto vital (los cuales se plantean 
en la adolescencia) como la culminaci칩n de la 
formaci칩n universitaria, el inicio y la consolidaci칩n 
en la campo laboral-profesional, la estabilidad en 
las relaciones de pareja (relacionado con la crisis 
de intimidad versus aislamiento) y el anhelo de 
formar una familia. 
	</x2>
	<i2></i2>
	<v></v>
</p>