<?xml version='1.0' encoding='iso-8859-1'?>
<!DOCTYPE pregunta SYSTEM "./../../../../clase.dtd">
<p>
	<q0>
	</q0>
	<g0>
	</g0>
	<q>En la oración “Manuel le dijo adiós a María”, la 
forma pronominal le cumple la función de
	</q>
	<q2>	
	</q2>
	<as t="R" correcta="0">
		<a>objeto indirecto.</a>
		<a>Vobjeto directo.</a>
		<a>complemento circunstancial.</a>
		<a>complemento atributivo.</a>
		<a>complemento predicativo.</a>
	</as>	
	<x>A. 
	</x>
	<i></i>
	<x2>Tema: Predicado 
El predicado es todo lo que se dice del sujeto. 
Cuando el verbo es no copulativo puede presentar 
OD, OI, C. agente, C. circunstancial o predicativo. 

Análisis y argumentación 
El objeto indirecto es el ser u objeto que se bene- 
ficia o perjudica con la acción verbal. Se presenta 

	</x2>
	<i2></i2>
	<v></v>
</p>