<?xml version='1.0' encoding='iso-8859-1'?>
<!DOCTYPE pregunta SYSTEM "./../../../../clase.dtd">
<p>
	<q0>
	</q0>
	<g0>
	</g0>
	<q>En el Per√∫, el diseÒo de captaci√≥n de impuestos, 
tasas y contribuciones del sector p√∫blico es res- 
ponsabilidad del 
	</q>
	<q2>	
	</q2>
	<as t="R" correcta="0">
		<a>Ministerio de Econom√≠a y Finanzas.</a>
		<a>Congreso de la Rep√∫blica.</a>
		<a>Ministerio de la Producci√≥n.</a>
		<a>Banco Central de Reserva del Per√∫.</a>
		<a>Banco de la Naci√≥n.</a>
	</as>	
	<x>A.
	</x>
	<i></i>
	<x2>
	</x2>
	<i2></i2>
	<v></v>
</p>