<?xml version='1.0' encoding='iso-8859-1'?>
<!DOCTYPE pregunta SYSTEM "./../../../../clase.dtd">
<p>
	<q0>
	</q0>
	<g0>
	</g0>
	<q>Si la información obtenida por las sensaciones 
fuese precisa y constante, entonces 
	</q>
	<q2>	
	</q2>
	<as t="R" correcta="0">
		<a>el conocimiento sensible se convertiría en 
	objetivo.</a>
		<a>el escepticismo sería equivalente al realis- 
	mo ingenuo.</a>
		<a>ningún ser humano podría tener la misma 
	percepción.</a>
		<a>la fe ingenua en la verdad sensible sería 
	injustificada.</a>
		<a>todas las personas percibiríamos las mis- 
	mas ideas.</a>
	</as>	
	<x>A.
	</x>
	<i></i>
	<x2>Según el texto, los escépticos no creen en la objeti- 
vidad del conocimiento sensorial porque nuestras 
impresiones resultan imprecisas y variables a las 
circunstancias. Por lo tanto, se extrapola que si la 
información obtenida por los sentidos fuese pre- 
cisa y constante, la objetividad del conocimiento 
sensible sería válida. 
	</x2>
	<i2></i2>
	<v></v>
</p>