<?xml version='1.0' encoding='iso-8859-1'?>
<!DOCTYPE pregunta SYSTEM "./../../../../clase.dtd">
<p>
	<q0>
	</q0>
	<g0>
	</g0>
	<q>Cu谩l de los siguientes enunciados resume mejor 
el texto? 
	</q>
	<q2>	
	</q2>
	<as t="R" correcta="3">
		<a>La pr谩ctica religiosa de caciques rivales 
	de mandar esculpir y trasladar moais 
	crecientemente colosales diezm贸 irrever- 
	siblemente los bosques.</a>
		<a>La pobreza de los suelos y la construcci贸n 
	de grandes moais destruyeron bosques y 
	rompieron el equilibrio ecol贸gico de la isla 
	de Pascua.</a>
		<a>Los habitantes de la isla de Pascua co- 
	metieron, sin propon茅rselo, un ecocidio 
	irreversible movidos por sus creencias y 
	pr谩cticas religiosas.</a>
		<a>haca el 800 d. C., los inmigrantes poli- 
	nesios talaron los bosques para habilitar 
	terrenos de cultivo y produjeron involun- 
	tariamente una cat谩strofe ecol贸gica.</a>
		<a>La cat谩strofe ecol贸gica de la isla fue conse- 
	cuencia de la destrucci贸n de bosques, sin 
	reposici贸n, y de la pesca intensiva, durante 
	siglos.</a>
	</as>	
	<x>D.
	</x>
	<i></i>
	<x2>En s铆ntesis, el texto nos informa sobre algunas 
investigaciones realizadas en la isla de Pascua, 
concluyen que en el 800 d. C., aproxi- 
madamente, los inmigrantes polinesios talaron 
los bosques de palmeras gigantes de la isla para 
ampliar sus terrenos agr铆colas. No obstante, oca- 
sionaron sin querer un ecocidio, o sea, una cat谩s- 
trofe ecol贸gica de la cual no pudieron recuperarse. 
Esto ocurri贸 antes de la llegada de los europeos 
a la isla, donde solo quedaron como vestigios los 
impresionantes moais. 
	</x2>
	<i2></i2>
	<v></v>
</p>