<?xml version='1.0' encoding='iso-8859-1'?>
<!DOCTYPE pregunta SYSTEM "./../../../../clase.dtd">
<p>
	<q0>
	</q0>
	<g0>
	</g0>
	<q>Un patio cuadrado de 17 metros de lado se 
pavimentará con losetas cuadradas de igual 
dimensión. Si el patio tuviera 18 metros de lado, se 
necesitaría 140 losetas más del mismo tipo que las 
anteriores. ¿Cuánto mide el lado de cada loseta? 
	</q>
	<q2>	
	</q2>
	<as t="R" correcta="0">
		<a>0,5 m</a>
		<a>0,25 m</a>
		<a>0,7 m</a>
		<a>0,75 m</a>
		<a>0,35 m</a>
	</as>	
	<x>A.
	</x>
	<i></i>
	<x2>
	</x2>
	<i2></i2>
	<v></v>
</p>