<?xml version='1.0' encoding='iso-8859-1'?>
<!DOCTYPE pregunta SYSTEM "./../../../../clase.dtd">
<p>
	<q0>
	</q0>
	<g0>
	</g0>
	<q>La faja costera peruana tiene un clima caracterizado 
por un gran d茅ficit de agua que le da una confi- 
guraci贸n des茅rtica. En este contexto, 驴por qu茅 el 
fen贸meno de El Nio genera tanta preocupaci贸n? 
I.	Altera la temperatura del mar trastocando el 
	ecosistema marino. 
II.  Origina condiciones de estabilidad atmosf茅rica 
	en el mar cerca del litoral. 
III. Activa las cuencas torrenciales provocando 
	huaicos e inundaciones catastr贸ficas. 
IV.  Provoca escasa evaporaci贸n y ausencia de 
	lluvias por invasi贸n de aguas fr铆as. 
	</q>
	<q2>	
	</q2>
	<as r="R" correcta="4">
		<a>I y II</a>
		<a>II y III</a>
		<a>III y IV</a>
		<a>II y IV</a>
		<a>I y III</a>
	</as>	
	<x>E.</x>
	<i></i>
	<x2>
	</x2>
	<i2></i2>
	<v></v>
</p>